edr_query_parser/__init__.py
edr_query_parser/edr_query_parser.py
tests/__init__.py
tests/test_edr_query_parser.py
edr_query_parser-4.3.4.dist-info/LICENSE
edr_query_parser-4.3.4.dist-info/METADATA
edr_query_parser-4.3.4.dist-info/WHEEL
edr_query_parser-4.3.4.dist-info/top_level.txt
edr_query_parser-4.3.4.dist-info/RECORD
