Metadata-Version: 2.1
Name: edr-query-parser
Version: 4.3.4
Summary: Environmental data retrieval API query parser
Home-page: https://github.com/r0w4n/edr_query_parser
Author: r0w4n
Author-email: r0w4n@nuisance.com
Classifier: Programming Language :: Python :: 3.6
Classifier: Programming Language :: Python :: 3.7
Classifier: Programming Language :: Python :: 3.8
Classifier: Programming Language :: Python :: 3.9
Classifier: Programming Language :: Python :: 3.10
Classifier: License :: OSI Approved :: GNU General Public License v3 (GPLv3)
Classifier: Operating System :: OS Independent
Classifier: Development Status :: 5 - Production/Stable
Requires-Python: >=3.6
License-File: LICENSE
Requires-Dist: python-dateutil
Requires-Dist: geomet
